neurobridge/__init__.py
neurobridge/bridge.py
neurobridge/core.py
neurobridge/dense.py
neurobridge/dense_connections.py
neurobridge/engine.py
neurobridge/globals.py
neurobridge/group.py
neurobridge/group_connections.py
neurobridge/monitors.py
neurobridge/neurons.py
neurobridge/utils.py
neurobridge/examples/01_basic_simulation.py
neurobridge/examples/02_stdp_learning.py
neurobridge/examples/03_multi_gpu.py
neurobridge/examples/04_ring_network.py
neurobridge/examples/05_pattern_recognition.py
neurobridge/examples/lib_example_01_multipleGPUs.py
neurobridge/examples/lib_example_02.1_oneGPU_profiling.py
neurobridge/examples/lib_example_02_oneGPU.py
neurobridge/examples/lib_example_03_twoGPUs.py
neurobridge/examples/lib_example_04.py
neurobridge/examples/old/all_gather_benchmark_01.py
neurobridge/examples/old/isend_irecev_example.py
neurobridge/examples/old/minimal_simulator.py
neurobridge/examples/old/pythonic_api.py
neurobridge/examples/old/simplest_isend_irecv_example.py
neurobridge/examples/old/test_distributed_bridge.py
neurobridge/examples/old/test_distributed_communication.py
neurobridge/examples/old/test_local_bridge.py
neurobridge/examples/old/test_multi_gpu_axonal_bridge_allgather.py
neurobridge/examples/old/test_nccl_bridge.py
neurobridge/tests/unit_tests.py
snn_neurobridge-0.1.2.dist-info/METADATA
snn_neurobridge-0.1.2.dist-info/WHEEL
snn_neurobridge-0.1.2.dist-info/top_level.txt
snn_neurobridge-0.1.2.dist-info/RECORD
